pyclerk/__init__.py
pyclerk/pyclerk.py
pyclerk/response_formats.py
pyclerk/endpoints/__init__.py
pyclerk/endpoints/_endpoint.py
pyclerk/endpoints/bulk.py
pyclerk/endpoints/cases.py
pyclerk/endpoints/citations.py
pyclerk/endpoints/courts.py
pyclerk/endpoints/jurisdictions.py
pyclerk/endpoints/ngrams.py
pyclerk/endpoints/reporters.py
pyclerk/endpoints/user_history.py
pyclerk/endpoints/volumes.py
pyclerk-0.0.1.dist-info/LICENSE
pyclerk-0.0.1.dist-info/METADATA
pyclerk-0.0.1.dist-info/WHEEL
pyclerk-0.0.1.dist-info/top_level.txt
pyclerk-0.0.1.dist-info/RECORD
