Metadata-Version: 2.1
Name: pyclerk
Version: 0.0.1
Summary: Use python to access all U.S. caselaw through the Harvard Law School Library.
Home-page: https://github.com/rgioai/caselaw-access-project
Author: Ryan Giarusso
Author-email: rgiarusso@jd20.law.harvard.edu
License: UNKNOWN
Platform: UNKNOWN
Classifier: Programming Language :: Python :: 3
Classifier: License :: OSI Approved :: MIT License
Classifier: Operating System :: OS Independent
Requires-Python: >3.6
